tri_api/__init__.py
tri_api-5.0.0.dist-info/licenses/LICENSE
tri_api-5.0.0.dist-info/METADATA
tri_api-5.0.0.dist-info/WHEEL
tri_api-5.0.0.dist-info/top_level.txt
tri_api-5.0.0.dist-info/RECORD
