Metadata-Version: 2.4
Name: tri.api
Version: 5.0.0
Summary: Client library for TriOptima APIs
Home-page: https://www.trioptima.com/
Author: TriOptima
Author-email: dl-tri.api@osttra.com
License: BSD
Classifier: Programming Language :: Python :: 3
Classifier: Operating System :: OS Independent
Classifier: Development Status :: 5 - Production/Stable
Classifier: Intended Audience :: Developers
Classifier: License :: OSI Approved :: BSD License
Classifier: Natural Language :: English
Requires-Python: >=3.6
License-File: LICENSE
Requires-Dist: requests
Dynamic: description
Dynamic: license-file
